{"_default": {"1": {"Chess_national_ID_Player_1": 12345, "Chess_national_ID_Player_2": 54321, "Winner": "OI321"}, "2": {"Chess_national_ID_Player_1": 56789, "Chess_national_ID_Player_2": 98765, "Winner": "OI321"}, "3": {"Chess_national_ID_Player_1": 12345, "Chess_national_ID_Player_2": 56789, "Winner": "OI321"}, "4": {"Chess_national_ID_Player_1": 54321, "Chess_national_ID_Player_2": 98765, "Winner": "OI321"}, "5": {"Chess_national_ID_Player_1": 12345, "Chess_national_ID_Player_2": 54321, "Winner": "OI321"}, "6": {"Chess_national_ID_Player_1": 12345, "Chess_national_ID_Player_2": 54321, "Winner": "OI321"}, "7": {"Chess_national_ID_Player_1": 56789, "Chess_national_ID_Player_2": 98765, "Winner": "OI321"}, "8": {"Chess_national_ID_Player_1": 12345, "Chess_national_ID_Player_2": 56789, "Winner": "OI321"}, "9": {"Chess_national_ID_Player_1": 54321, "Chess_national_ID_Player_2": 98765, "Winner": "OI321"}, "10": {"Chess_national_ID_Player_1": 12345, "Chess_national_ID_Player_2": 54321, "Winner": "OI321"}, "11": {"Chess_national_ID_Player_1": 56789, "Chess_national_ID_Player_2": 98765, "Winner": "OI321"}, "12": {"Chess_national_ID_Player_1": 12345, "Chess_national_ID_Player_2": 56789, "Winner": "OI321"}, "13": {"Chess_national_ID_Player_1": 54321, "Chess_national_ID_Player_2": 98765, "Winner": "OI321"}, "14": {"Chess_national_ID_Player_1": 12345, "Chess_national_ID_Player_2": 54321, "Winner": "OI321"}, "15": {"Chess_national_ID_Player_1": 56789, "Chess_national_ID_Player_2": 98765, "Winner": "OI321"}, "16": {"Chess_national_ID_Player_1": 12345, "Chess_national_ID_Player_2": 54321, "Winner": "OI321"}, "17": {"Chess_national_ID_Player_1": 56789, "Chess_national_ID_Player_2": 98765, "Winner": "OI321"}, "18": {"Chess_national_ID_Player_1": 12345, "Chess_national_ID_Player_2": 56789, "Winner": "OI321"}, "19": {"Chess_national_ID_Player_1": 54321, "Chess_national_ID_Player_2": 98765, "Winner": "OI321"}, "20": {"Chess_national_ID_Player_1": 12345, "Chess_national_ID_Player_2": 54321, "Winner": "OI321"}, "21": {"Chess_national_ID_Player_1": 56789, "Chess_national_ID_Player_2": 98765, "Winner": "OI321"}, "22": {"Chess_national_ID_Player_1": 12345, "Chess_national_ID_Player_2": 54321, "Winner": "OI321"}, "23": {"Chess_national_ID_Player_1": 56789, "Chess_national_ID_Player_2": 98765, "Winner": "OI321"}, "24": {"Chess_national_ID_Player_1": 12345, "Chess_national_ID_Player_2": 56789, "Winner": "OI321"}, "25": {"Chess_national_ID_Player_1": 54321, "Chess_national_ID_Player_2": 98765, "Winner": "OI321"}, "26": {"Chess_national_ID_Player_1": 12345, "Chess_national_ID_Player_2": 54321, "Winner": "OI321"}, "27": {"Chess_national_ID_Player_1": 56789, "Chess_national_ID_Player_2": 98765, "Winner": "OI321"}, "28": {"Chess_national_ID_Player_1": 12345, "Chess_national_ID_Player_2": 54321, "Winner": "OI321"}, "29": {"Chess_national_ID_Player_1": 56789, "Chess_national_ID_Player_2": 98765, "Winner": "OI321"}, "30": {"Chess_national_ID_Player_1": 12345, "Chess_national_ID_Player_2": 56789, "Winner": "OI321"}, "31": {"Chess_national_ID_Player_1": 54321, "Chess_national_ID_Player_2": 98765, "Winner": "OI321"}, "32": {"Chess_national_ID_Player_1": 12345, "Chess_national_ID_Player_2": 54321, "Winner": "OI321"}, "33": {"Chess_national_ID_Player_1": 56789, "Chess_national_ID_Player_2": 98765, "Winner": "OI321"}, "34": {"Chess_national_ID_Player_1": 12345, "Chess_national_ID_Player_2": 56789, "Winner": "OI321"}, "35": {"Chess_national_ID_Player_1": 54321, "Chess_national_ID_Player_2": 98765, "Winner": "OI321"}, "36": {"Chess_national_ID_Player_1": 12345, "Chess_national_ID_Player_2": 54321, "Winner": "OI321"}, "37": {"Chess_national_ID_Player_1": 56789, "Chess_national_ID_Player_2": 98765, "Winner": "OI321"}, "38": {"Chess_national_ID_Player_1": 12345, "Chess_national_ID_Player_2": 56789, "Winner": "OI321"}, "39": {"Chess_national_ID_Player_1": 54321, "Chess_national_ID_Player_2": 98765, "Winner": "OI321"}, "40": {"Chess_national_ID_Player_1": 12345, "Chess_national_ID_Player_2": 54321, "Winner": "OI321"}, "41": {"Chess_national_ID_Player_1": 56789, "Chess_national_ID_Player_2": 98765, "Winner": "OI321"}, "42": {"Chess_national_ID_Player_1": 12345, "Chess_national_ID_Player_2": 56789, "Winner": "OI321"}, "43": {"Chess_national_ID_Player_1": 54321, "Chess_national_ID_Player_2": 98765, "Winner": "OI321"}, "44": {"Chess_national_ID_Player_1": 12345, "Chess_national_ID_Player_2": 54321, "Winner": "OI321"}, "45": {"Chess_national_ID_Player_1": 12345, "Chess_national_ID_Player_2": 54321, "Winner": "OI321"}, "46": {"Chess_national_ID_Player_1": 56789, "Chess_national_ID_Player_2": 98765, "Winner": "OI321"}, "47": {"Chess_national_ID_Player_1": 12345, "Chess_national_ID_Player_2": 56789, "Winner": "OI321"}, "48": {"Chess_national_ID_Player_1": 54321, "Chess_national_ID_Player_2": 98765, "Winner": "OI321"}, "49": {"Chess_national_ID_Player_1": 12345, "Chess_national_ID_Player_2": 54321, "Winner": "OI321"}, "50": {"Chess_national_ID_Player_1": 56789, "Chess_national_ID_Player_2": 98765, "Winner": "OI321"}, "51": {"Chess_national_ID_Player_1": 12345, "Chess_national_ID_Player_2": 56789, "Winner": "OI321"}, "52": {"Chess_national_ID_Player_1": 54321, "Chess_national_ID_Player_2": 98765, "Winner": "OI321"}, "53": {"Chess_national_ID_Player_1": 12345, "Chess_national_ID_Player_2": 54321, "Winner": "OI321"}, "54": {"Chess_national_ID_Player_1": 56789, "Chess_national_ID_Player_2": 98765, "Winner": "OI321"}, "55": {"Chess_national_ID_Player_1": 12345, "Chess_national_ID_Player_2": 54321, "Winner": "OI321"}, "56": {"Chess_national_ID_Player_1": 56789, "Chess_national_ID_Player_2": 98765, "Winner": "OI321"}, "57": {"Chess_national_ID_Player_1": 12345, "Chess_national_ID_Player_2": 56789, "Winner": "OI321"}, "58": {"Chess_national_ID_Player_1": 54321, "Chess_national_ID_Player_2": 98765, "Winner": "OI321"}, "59": {"Chess_national_ID_Player_1": 12345, "Chess_national_ID_Player_2": 54321, "Winner": "OI321"}, "60": {"Chess_national_ID_Player_1": 12345, "Chess_national_ID_Player_2": 56789, "Winner": "OI321"}, "61": {"Chess_national_ID_Player_1": 12345, "Chess_national_ID_Player_2": 54321, "Winner": "OI321"}, "62": {"Chess_national_ID_Player_1": 56789, "Chess_national_ID_Player_2": 98765, "Winner": "OI321"}, "63": {"Chess_national_ID_Player_1": 12345, "Chess_national_ID_Player_2": 54321, "Winner": "OI321"}, "64": {"Chess_national_ID_Player_1": 56789, "Chess_national_ID_Player_2": 98765, "Winner": "OI321"}, "65": {"Chess_national_ID_Player_1": 12345, "Chess_national_ID_Player_2": 56789, "Winner": "OI321"}, "66": {"Chess_national_ID_Player_1": 54321, "Chess_national_ID_Player_2": 98765, "Winner": "OI321"}, "67": {"Chess_national_ID_Player_1": 12345, "Chess_national_ID_Player_2": 54321, "Winner": "OI321"}, "68": {"Chess_national_ID_Player_1": 56789, "Chess_national_ID_Player_2": 98765, "Winner": "OI321"}, "69": {"Chess_national_ID_Player_1": 12345, "Chess_national_ID_Player_2": 56789, "Winner": "OI321"}, "70": {"Chess_national_ID_Player_1": 12345, "Chess_national_ID_Player_2": 54321, "Winner": "OI321"}, "71": {"Chess_national_ID_Player_1": 12345, "Chess_national_ID_Player_2": 54321, "Winner": "OI321"}, "72": {"Chess_national_ID_Player_1": 12345, "Chess_national_ID_Player_2": 54321, "Winner": "OI321"}, "73": {"Chess_national_ID_Player_1": 56789, "Chess_national_ID_Player_2": 98765, "Winner": "OI321"}, "74": {"Chess_national_ID_Player_1": 12345, "Chess_national_ID_Player_2": 56789, "Winner": "OI321"}, "75": {"Chess_national_ID_Player_1": 54321, "Chess_national_ID_Player_2": 98765, "Winner": "OI321"}, "76": {"Chess_national_ID_Player_1": 12345, "Chess_national_ID_Player_2": 54321, "Winner": "OI321"}, "77": {"Chess_national_ID_Player_1": 56789, "Chess_national_ID_Player_2": 98765, "Winner": "OI321"}, "78": {"Chess_national_ID_Player_1": 12345, "Chess_national_ID_Player_2": 56789, "Winner": "OI321"}, "79": {"Chess_national_ID_Player_1": 54321, "Chess_national_ID_Player_2": 98765, "Winner": "OI321"}, "80": {"Chess_national_ID_Player_1": 12345, "Chess_national_ID_Player_2": 54321, "Winner": "OI321"}, "81": {"Chess_national_ID_Player_1": 56789, "Chess_national_ID_Player_2": 98765, "Winner": "OI321"}, "82": {"Chess_national_ID_Player_1": 12345, "Chess_national_ID_Player_2": 56789, "Winner": "OI321"}, "83": {"Chess_national_ID_Player_1": 54321, "Chess_national_ID_Player_2": 98765, "Winner": "OI321"}, "84": {"Chess_national_ID_Player_1": 12345, "Chess_national_ID_Player_2": 54321, "Winner": "OI321"}, "85": {"Chess_national_ID_Player_1": 56789, "Chess_national_ID_Player_2": 98765, "Winner": "OI321"}, "86": {"Chess_national_ID_Player_1": 12345, "Chess_national_ID_Player_2": 56789, "Winner": "OI321"}, "87": {"Chess_national_ID_Player_1": 54321, "Chess_national_ID_Player_2": 98765, "Winner": "OI321"}, "88": {"Chess_national_ID_Player_1": 12345, "Chess_national_ID_Player_2": 54321, "Winner": "OI321"}, "89": {"Chess_national_ID_Player_1": 56789, "Chess_national_ID_Player_2": 98765, "Winner": "OI321"}, "90": {"Chess_national_ID_Player_1": 12345, "Chess_national_ID_Player_2": 56789, "Winner": "OI321"}, "91": {"Chess_national_ID_Player_1": 54321, "Chess_national_ID_Player_2": 98765, "Winner": "OI321"}, "92": {"Chess_national_ID_Player_1": 12345, "Chess_national_ID_Player_2": 54321, "Winner": "OI321"}, "93": {"Chess_national_ID_Player_1": 56789, "Chess_national_ID_Player_2": 98765, "Winner": "OI321"}, "94": {"Chess_national_ID_Player_1": 12345, "Chess_national_ID_Player_2": 56789, "Winner": "OI321"}, "95": {"Chess_national_ID_Player_1": 12345, "Chess_national_ID_Player_2": 54321, "Winner": "OI321"}, "96": {"Chess_national_ID_Player_1": 56789, "Chess_national_ID_Player_2": 98765, "Winner": "OI321"}, "97": {"Chess_national_ID_Player_1": 12345, "Chess_national_ID_Player_2": 56789, "Winner": "OI321"}, "98": {"Chess_national_ID_Player_1": 54321, "Chess_national_ID_Player_2": 98765, "Winner": "OI321"}, "99": {"Chess_national_ID_Player_1": 12345, "Chess_national_ID_Player_2": 54321, "Winner": "OI321"}, "100": {"Chess_national_ID_Player_1": 56789, "Chess_national_ID_Player_2": 98765, "Winner": "OI321"}, "101": {"Chess_national_ID_Player_1": 12345, "Chess_national_ID_Player_2": 54321, "Winner": "OI321"}, "102": {"Chess_national_ID_Player_1": "JH345", "Chess_national_ID_Player_2": "OI321", "Winner": "OI321"}, "103": {"Chess_national_ID_Player_1": "DR789", "Chess_national_ID_Player_2": "TR765", "Winner": "OI321"}, "104": {"Chess_national_ID_Player_1": "JH345", "Chess_national_ID_Player_2": "DR789", "Winner": "OI321"}, "105": {"Chess_national_ID_Player_1": "OI321", "Chess_national_ID_Player_2": "TR765", "Winner": "OI321"}, "106": {"Chess_national_ID_Player_1": "JH345", "Chess_national_ID_Player_2": "OI321", "Winner": "OI321"}, "107": {"Chess_national_ID_Player_1": "DR789", "Chess_national_ID_Player_2": "TR765", "Winner": "OI321"}, "108": {"Chess_national_ID_Player_1": "JH345", "Chess_national_ID_Player_2": "OI321", "Winner": "OI321"}, "109": {"Chess_national_ID_Player_1": "DR789", "Chess_national_ID_Player_2": "TR765", "Winner": "OI321"}, "110": {"Chess_national_ID_Player_1": "JH345", "Chess_national_ID_Player_2": "OI321", "Winner": "OI321"}, "111": {"Chess_national_ID_Player_1": "JH345", "Chess_national_ID_Player_2": "OI321", "Winner": "OI321"}, "112": {"Chess_national_ID_Player_1": "DR789", "Chess_national_ID_Player_2": "TR765", "Winner": "OI321"}, "113": {"Chess_national_ID_Player_1": "JH345", "Chess_national_ID_Player_2": "DR789", "Winner": "OI321"}, "114": {"Chess_national_ID_Player_1": "OI321", "Chess_national_ID_Player_2": "TR765", "Winner": "OI321"}, "115": {"Chess_national_ID_Player_1": "JH345", "Chess_national_ID_Player_2": "OI321", "Winner": "OI321"}, "116": {"Chess_national_ID_Player_1": "DR789", "Chess_national_ID_Player_2": "TR765", "Winner": "OI321"}, "117": {"Chess_national_ID_Player_1": "JH345", "Chess_national_ID_Player_2": "OI321", "Winner": "OI321"}, "118": {"Chess_national_ID_Player_1": "DR789", "Chess_national_ID_Player_2": "TR765", "Winner": "OI321"}, "119": {"Chess_national_ID_Player_1": "JH345", "Chess_national_ID_Player_2": "DR789", "Winner": "OI321"}, "120": {"Chess_national_ID_Player_1": "OI321", "Chess_national_ID_Player_2": "TR765", "Winner": "OI321"}, "121": {"Chess_national_ID_Player_1": "JH345", "Chess_national_ID_Player_2": "OI321", "Winner": "OI321"}, "122": {"Chess_national_ID_Player_1": "DR789", "Chess_national_ID_Player_2": "TR765", "Winner": "OI321"}, "123": {"Chess_national_ID_Player_1": "JH345", "Chess_national_ID_Player_2": "DR789", "Winner": "OI321"}, "124": {"Chess_national_ID_Player_1": "OI321", "Chess_national_ID_Player_2": "TR765", "Winner": "OI321"}, "125": {"Chess_national_ID_Player_1": "JH345", "Chess_national_ID_Player_2": "OI321", "Winner": "OI321"}, "126": {"Chess_national_ID_Player_1": "DR789", "Chess_national_ID_Player_2": "TR765", "Winner": "OI321"}, "127": {"Chess_national_ID_Player_1": "JH345", "Chess_national_ID_Player_2": "DR789", "Winner": "OI321"}, "128": {"Chess_national_ID_Player_1": "OI321", "Chess_national_ID_Player_2": "TR765", "Winner": "OI321"}, "129": {"Chess_national_ID_Player_1": "JH345", "Chess_national_ID_Player_2": "OI321", "Winner": "OI321"}, "130": {"Chess_national_ID_Player_1": "DR789", "Chess_national_ID_Player_2": "TR765", "Winner": "OI321"}, "131": {"Chess_national_ID_Player_1": "JH345", "Chess_national_ID_Player_2": "DR789", "Winner": "OI321"}, "132": {"Chess_national_ID_Player_1": "OI321", "Chess_national_ID_Player_2": "TR765", "Winner": "OI321"}, "133": {"Chess_national_ID_Player_1": "JH345", "Chess_national_ID_Player_2": "OI321", "Winner": "OI321"}, "134": {"Chess_national_ID_Player_1": "DR789", "Chess_national_ID_Player_2": "TR765", "Winner": "OI321"}, "135": {"Chess_national_ID_Player_1": "JH345", "Chess_national_ID_Player_2": "OI321", "Winner": "OI321"}, "136": {"Chess_national_ID_Player_1": "DR789", "Chess_national_ID_Player_2": "TR765", "Winner": "OI321"}, "137": {"Chess_national_ID_Player_1": "JH345", "Chess_national_ID_Player_2": "DR789", "Winner": "OI321"}, "138": {"Chess_national_ID_Player_1": "OI321", "Chess_national_ID_Player_2": "TR765", "Winner": "OI321"}, "139": {"Chess_national_ID_Player_1": "JH345", "Chess_national_ID_Player_2": "OI321", "Winner": "OI321"}, "140": {"Chess_national_ID_Player_1": "DR789", "Chess_national_ID_Player_2": "TR765", "Winner": "OI321"}, "141": {"Chess_national_ID_Player_1": "JH345", "Chess_national_ID_Player_2": "DR789", "Winner": "OI321"}, "142": {"Chess_national_ID_Player_1": "OI321", "Chess_national_ID_Player_2": "TR765", "Winner": "OI321"}}}